Metadata-Version: 2.1
Name: epub_toc
Version: 1.0.0
Summary: A Python tool for extracting table of contents from EPUB files with hierarchical structure support
Home-page: https://github.com/almazilaletdinov/epub_toc
Author: Almaz Ilaletdinov
Author-email: a.ilaletdinov@yandex.ru
Project-URL: Documentation, https://github.com/almazilaletdinov/epub_toc/docs
Project-URL: Source, https://github.com/almazilaletdinov/epub_toc
Project-URL: Tracker, https://github.com/almazilaletdinov/epub_toc/issues
Keywords: epub,ebook,toc,table of contents,parser,ebook-tools
Classifier: Development Status :: 4 - Beta
Classifier: Intended Audience :: Developers
Classifier: License :: OSI Approved :: MIT License
Classifier: Programming Language :: Python :: 3
Classifier: Programming Language :: Python :: 3.7
Classifier: Programming Language :: Python :: 3.8
Classifier: Programming Language :: Python :: 3.9
Classifier: Programming Language :: Python :: 3.10
Classifier: Programming Language :: Python :: 3.11
Classifier: Operating System :: OS Independent
Classifier: Topic :: Software Development :: Libraries :: Python Modules
Classifier: Topic :: Text Processing :: Markup
Requires-Python: >=3.7
License-File: LICENSE
Requires-Dist: epub_meta>=0.0.7
Requires-Dist: lxml>=4.9.3
Requires-Dist: beautifulsoup4>=4.12.2
Requires-Dist: ebooklib>=0.18
Requires-Dist: tika>=2.6
Provides-Extra: dev
Requires-Dist: pytest>=7.4.3; extra == "dev"
Requires-Dist: pytest-cov>=4.1.0; extra == "dev"
Requires-Dist: pytest-mock>=3.12.0; extra == "dev"
Requires-Dist: black>=23.12.1; extra == "dev"
Requires-Dist: isort>=5.13.2; extra == "dev"
Requires-Dist: flake8>=7.0.0; extra == "dev"
Requires-Dist: mypy>=1.8.0; extra == "dev"
Requires-Dist: types-beautifulsoup4>=4.12.0.7; extra == "dev"
Requires-Dist: types-lxml>=2023.10.21; extra == "dev"
